geoskey/__init__.py
geoskey/common.py
geoskey/geoskey.py
geoskey-0.0.1.dist-info/LICENSE
geoskey-0.0.1.dist-info/METADATA
geoskey-0.0.1.dist-info/WHEEL
geoskey-0.0.1.dist-info/entry_points.txt
geoskey-0.0.1.dist-info/top_level.txt
geoskey-0.0.1.dist-info/RECORD
