Metadata-Version: 2.1
Name: geoskey
Version: 0.0.1
Summary: A python package demo for geospatial analysis
Author-email: Khaled Hammami <khalled.hammami@gmail.com>
License: MIT License
Project-URL: Homepage, https://github.com/HammamiKhaled/geoskey
Keywords: geoskey
Classifier: Intended Audience :: Developers
Classifier: License :: OSI Approved :: MIT License
Classifier: Natural Language :: English
Classifier: Programming Language :: Python :: 3.8
Classifier: Programming Language :: Python :: 3.9
Classifier: Programming Language :: Python :: 3.10
Classifier: Programming Language :: Python :: 3.11
Classifier: Programming Language :: Python :: 3.12
Requires-Python: >=3.8
License-File: LICENSE
Requires-Dist: numpy
Provides-Extra: all
Requires-Dist: geoskey[extra]; extra == "all"
Provides-Extra: extra
Requires-Dist: pandas; extra == "extra"
